warframe_metrics/analysis/__init__.py
warframe_metrics/analysis/models.py
warframe_metrics/main.py
warframe_metrics/market/__init__.py
warframe_metrics/market/prime.py
warframe_metrics/utils/__init__.py
warframe_metrics/utils/collect_data.py
warframe_metrics/utils/constants.py
warframe_metrics/utils/schema.py
warframe_metrics-0.1.3.dist-info/LICENSE.rst
warframe_metrics-0.1.3.dist-info/WHEEL
warframe_metrics-0.1.3.dist-info/METADATA
warframe_metrics-0.1.3.dist-info/RECORD
