Metadata-Version: 2.1
Name: warframe-metrics
Version: 0.1.3
Summary: Warframe market metrics package.
Home-page: https://github.com/rajivsarvepalli/warframe-metrics
License: MIT
Keywords: warframe,warframe market,warframe market data
Author: Rajiv Sarvepalli
Author-email: rajiv@sarvepalli.net
Requires-Python: >=3.7.1,<4.0.0
Classifier: Development Status :: 2 - Pre-Alpha
Classifier: Intended Audience :: Developers
Classifier: License :: OSI Approved :: MIT License
Classifier: Natural Language :: English
Classifier: Programming Language :: Python
Classifier: Programming Language :: Python :: 3
Classifier: Programming Language :: Python :: 3.7
Classifier: Programming Language :: Python :: 3.8
Classifier: Programming Language :: Python :: 3.9
Requires-Dist: alive-progress (>=1.6.2,<2.0.0)
Requires-Dist: desert (>=2020.11.18,<2021.0.0)
Requires-Dist: pandas (>=1.2.4,<2.0.0)
Requires-Dist: requests (>=2.25.1,<3.0.0)
Project-URL: Changelog, https://github.com/rajivsarvepalli/warframe-metrics/releases
Project-URL: Documentation, https://warframe-metrics.readthedocs.io
Project-URL: Repository, https://github.com/rajivsarvepalli/warframe-metrics
